topsis_dikshant_102303201/__init__.py
topsis_dikshant_102303201/topsis.py
topsis_dikshant_102303201-0.1.2.dist-info/licenses/LICENSE
topsis_dikshant_102303201-0.1.2.dist-info/METADATA
topsis_dikshant_102303201-0.1.2.dist-info/WHEEL
topsis_dikshant_102303201-0.1.2.dist-info/entry_points.txt
topsis_dikshant_102303201-0.1.2.dist-info/top_level.txt
topsis_dikshant_102303201-0.1.2.dist-info/RECORD
